LICENSE
README.md
setup.py
em_st_artifacts/__init__.py
em_st_artifacts/emotional_math.py
em_st_artifacts/sample.py
em_st_artifacts/libs/macos/libEmStArtifacts.dylib
em_st_artifacts/libs/x64/em_st_artifacts-x64.dll
em_st_artifacts/libs/x86/em_st_artifacts-x86.dll
em_st_artifacts/utils/EmotionalMathException.py
em_st_artifacts/utils/__init__.py
em_st_artifacts/utils/lib_settings.py
em_st_artifacts/utils/support_classes.py
pyem_st_artifacts.egg-info/PKG-INFO
pyem_st_artifacts.egg-info/SOURCES.txt
pyem_st_artifacts.egg-info/dependency_links.txt
pyem_st_artifacts.egg-info/top_level.txt